src/__init__.py
src/main.py
python_lab-0.3a0.dist-info/LICENSE
python_lab-0.3a0.dist-info/METADATA
python_lab-0.3a0.dist-info/WHEEL
python_lab-0.3a0.dist-info/entry_points.txt
python_lab-0.3a0.dist-info/top_level.txt
python_lab-0.3a0.dist-info/RECORD
