Metadata-Version: 2.1
Name: python-lab
Version: 0.3a0
Summary: A workspace dedicated to experimenting with and exploring Python concepts.
Author: Team VeHost
License: MIT
Classifier: Programming Language :: Python :: 3
Classifier: License :: OSI Approved :: MIT License
Classifier: Operating System :: OS Independent
Requires-Python: >=3.6
License-File: LICENSE
Requires-Dist: certifi==2024.8.30
Requires-Dist: cffi==1.17.1
Requires-Dist: charset-normalizer==3.4.0
Requires-Dist: cryptography==43.0.3
Requires-Dist: docutils==0.21.2
Requires-Dist: idna==3.10
Requires-Dist: importlib-metadata==8.5.0
Requires-Dist: iniconfig==2.0.0
Requires-Dist: jaraco.classes==3.4.0
Requires-Dist: jaraco.context==6.0.1
Requires-Dist: jaraco.functools==4.1.0
Requires-Dist: jeepney==0.8.0
Requires-Dist: keyring==25.4.1
Requires-Dist: markdown-it-py==3.0.0
Requires-Dist: mdurl==0.1.2
Requires-Dist: more-itertools==10.5.0
Requires-Dist: nh3==0.2.18
Requires-Dist: packaging==24.1
Requires-Dist: pkginfo==1.10.0
Requires-Dist: pluggy==1.5.0
Requires-Dist: pycparser==2.22
Requires-Dist: Pygments==2.18.0
Requires-Dist: pytest==8.3.3
Requires-Dist: readme-renderer==44.0
Requires-Dist: requests==2.32.3
Requires-Dist: requests-toolbelt==1.0.0
Requires-Dist: rfc3986==2.0.0
Requires-Dist: rich==13.9.3
Requires-Dist: SecretStorage==3.3.3
Requires-Dist: setuptools==75.2.0
Requires-Dist: twine==5.1.1
Requires-Dist: urllib3==2.2.3
Requires-Dist: wheel==0.44.0
Requires-Dist: zipp==3.20.2
